pytorch_kinematics/__init__.py
pytorch_kinematics/cfg.py
pytorch_kinematics/chain.py
pytorch_kinematics/frame.py
pytorch_kinematics/ik.py
pytorch_kinematics/jacobian.py
pytorch_kinematics/mjcf.py
pytorch_kinematics/sdf.py
pytorch_kinematics/urdf.py
pytorch_kinematics/transforms/__init__.py
pytorch_kinematics/transforms/math.py
pytorch_kinematics/transforms/perturbation.py
pytorch_kinematics/transforms/rotation_conversions.py
pytorch_kinematics/transforms/so3.py
pytorch_kinematics/transforms/transform3d.py
pytorch_kinematics/urdf_parser_py/__init__.py
pytorch_kinematics/urdf_parser_py/sdf.py
pytorch_kinematics/urdf_parser_py/urdf.py
pytorch_kinematics/urdf_parser_py/xml_reflection/__init__.py
pytorch_kinematics/urdf_parser_py/xml_reflection/basics.py
pytorch_kinematics/urdf_parser_py/xml_reflection/core.py
pytorch_kinematics-0.7.6.dist-info/LICENSE.txt
pytorch_kinematics-0.7.6.dist-info/METADATA
pytorch_kinematics-0.7.6.dist-info/WHEEL
pytorch_kinematics-0.7.6.dist-info/top_level.txt
pytorch_kinematics-0.7.6.dist-info/RECORD
